LICENSE
MANIFEST.in
README.rst
blohg_tumblelog.py
setup.py
blohg_tumblelog.egg-info/PKG-INFO
blohg_tumblelog.egg-info/SOURCES.txt
blohg_tumblelog.egg-info/dependency_links.txt
blohg_tumblelog.egg-info/not-zip-safe
blohg_tumblelog.egg-info/requires.txt
blohg_tumblelog.egg-info/top_level.txt